Rudraya/Ensemble/__init__.py
Rudraya/Evaluation/__init__.py
Rudraya/Filters/__init__.py
Rudraya/TimeDominAnalysis/__init__.py
Rudraya-0.19.dist-info/LICENCE
Rudraya-0.19.dist-info/METADATA
Rudraya-0.19.dist-info/WHEEL
Rudraya-0.19.dist-info/top_level.txt
Rudraya-0.19.dist-info/RECORD
