Metadata-Version: 2.1
Name: Rudraya
Version: 0.19
Summary: UNKNOWN
Author: ['Tushar Kolekar', 'Sameer Sayyad']
Author-email: tusharkolekar24@gmail.com
License: MIT
Platform: UNKNOWN
Classifier: License :: OSI Approved :: MIT License
Classifier: Operating System :: OS Independent
Classifier: Programming Language :: Python :: 3.6
License-File: LICENCE
Requires-Dist: numpy
Requires-Dist: sklearn
Requires-Dist: pandas
Requires-Dist: seaborn
Requires-Dist: statsmodels
